[
  { "-----------------------------------------------------------------------------------------" },
  { "type": "input", "message": "start zahlenraten" },
  { "type": "output", "message": "[3m[34mzahlenraten[0m: Eine zufällige Zahl zwischen 1 und 100 wurde erstellt. Versuche sie nun zu erraten :)" },
  { "type": "input", "message": "45" },
  { "type": "variable", "message": "Variable 'input' geändert: von -1 auf 45" },
  { "type": "variable", "message": "Variable 'versuche' geändert: von 0 auf 1" },
  { "type": "output", "message": "[3m[34mzahlenraten[0m: Deine Zahl ist zu klein" },
  { "type": "input", "message": "67" },
  { "type": "variable", "message": "Variable 'input' geändert: von 45 auf 67" },
  { "type": "variable", "message": "Variable 'versuche' geändert: von 1 auf 2" },
  { "type": "output", "message": "[3m[34mzahlenraten[0m: Deine Zahl ist zu groß" },
  { "type": "input", "message": "55" },
  { "type": "variable", "message": "Variable 'input' geändert: von 67 auf 55" },
  { "type": "variable", "message": "Variable 'versuche' geändert: von 2 auf 3" },
  { "type": "output", "message": "[3m[34mzahlenraten[0m: Deine Zahl ist zu klein" },
  { "type": "input", "message": "60" },
  { "type": "variable", "message": "Variable 'input' geändert: von 55 auf 60" },
  { "type": "variable", "message": "Variable 'versuche' geändert: von 3 auf 4" },
  { "type": "output", "message": "[3m[34mzahlenraten[0m: Deine Zahl ist zu groß" },
  { "type": "input", "message": "57" },
  { "type": "variable", "message": "Variable 'input' geändert: von 60 auf 57" },
  { "type": "variable", "message": "Variable 'versuche' geändert: von 4 auf 5" },
  { "type": "output", "message": "[3m[34mzahlenraten[0m: Deine Zahl ist zu groß" },
  { "type": "input", "message": "56" },
  { "type": "variable", "message": "Variable 'input' geändert: von 57 auf 56" },
  { "type": "variable", "message": "Variable 'versuche' geändert: von 5 auf 6" },
  { "type": "output", "message": "[3m[34mzahlenraten[0m: Glückwunsch. Du Hast die Zahl 56 mit 6 Versuchen richtig erraten!" },
  { "type": "output", "message": "[3mDie Methode [34mzahlenraten[0m[3m wurde beendet!" },
  { "-----------------------------------------------------------------------------------------" },
  { "type": "input", "message": "stop" },
  { "type": "output", "message": "Programm wird beendet..." }
]